Metadata-Version: 2.1
Name: statstical-plot
Version: 0.1
Summary: Statistical plotting with good aesthetics.
Home-page: https://github.com/ChenLiu-1996/StatsPlot
Author: Chen Liu
Author-email: chen.liu.cl2482@yale.edu
License: MIT
Keywords: plotting,plot,statistical plotting,statistical plot
License-File: LICENSE.md
